LICENSE.md
MANIFEST.in
README.rst
setup.py
board/__init__.py
board/admin.py
board/models.py
board/tests.py
board/templatetags/__init__.py
board/templatetags/board_tags.py
django_board.egg-info/PKG-INFO
django_board.egg-info/SOURCES.txt
django_board.egg-info/dependency_links.txt
django_board.egg-info/not-zip-safe
django_board.egg-info/requires.txt
django_board.egg-info/top_level.txt