Metadata-Version: 1.1
Name: django-board
Version: 0.2.1
Summary: A Django app for managing an organisation's board members page.
Home-page: http://github.com/dominicrodger/django-board
Author: Dominic Rodger
Author-email: internet@dominicrodger.com
License: BSD
Platform: UNKNOWN
Classifier: Development Status :: 3 - Alpha
Classifier: Framework :: Django
Classifier: License :: OSI Approved :: BSD License
